pyspacemouse/__init__.py
pyspacemouse/pyspacemouse.py
pyspacemouse/pyspacemouse_cli.py
pyspacemouse-1.1.5.dist-info/METADATA
pyspacemouse-1.1.5.dist-info/WHEEL
pyspacemouse-1.1.5.dist-info/entry_points.txt
pyspacemouse-1.1.5.dist-info/licenses/LICENSE
pyspacemouse-1.1.5.dist-info/RECORD
