Metadata-Version: 2.4
Name: pyspacemouse
Version: 1.1.5
Summary: Multiplatform Python interface to the 3DConnexion Space Mouse - forked from pyspacenavigator
Project-URL: Documentation, https://spacemouse.kubaandrysek.cz
Project-URL: Issues, https://github.com/JakubAndrysek/pyspacemouse/issues
Project-URL: Source, https://github.com/JakubAndrysek/pyspacemouse
Author-email: Jakub Andrýsek <email@kubaandrysek.cz>
License-Expression: MIT
License-File: LICENSE
Keywords: 3d,3d-mouse,3dconnection,6 DoF,HID,open-source,pyspacemouse,python,spacemouse,spacenavigator
Classifier: Development Status :: 4 - Beta
Classifier: License :: OSI Approved :: MIT License
Classifier: Operating System :: OS Independent
Classifier: Programming Language :: Python :: 3
Classifier: Programming Language :: Python :: 3 :: Only
Classifier: Programming Language :: Python :: 3.8
Classifier: Programming Language :: Python :: 3.9
Classifier: Programming Language :: Python :: 3.10
Classifier: Programming Language :: Python :: 3.11
Classifier: Programming Language :: Python :: 3.12
Classifier: Programming Language :: Python :: 3.13
Classifier: Topic :: System :: Hardware :: Universal Serial Bus (USB) :: Human Interface Device (HID)
Requires-Python: >=3.8
Requires-Dist: easyhid
Provides-Extra: dev
Requires-Dist: build; extra == 'dev'
Requires-Dist: pytest-cov>=4.0; extra == 'dev'
Requires-Dist: pytest>=7.0; extra == 'dev'
Requires-Dist: ruff>=0.12.0; extra == 'dev'
Requires-Dist: twine; extra == 'dev'
Provides-Extra: docs
Requires-Dist: mkdocs; extra == 'docs'
Requires-Dist: mkdocs-git-revision-date-localized-plugin; extra == 'docs'
Requires-Dist: mkdocs-glightbox; extra == 'docs'
Requires-Dist: mkdocs-material; extra == 'docs'
Requires-Dist: mkdocs-open-in-new-tab; extra == 'docs'
Requires-Dist: mkdocs-redirects; extra == 'docs'
Requires-Dist: mkdoxy; extra == 'docs'
